MANIFEST.in
README.rst
setup.py
kikyopp/__init__.py
kikyopp/_patch.py
kikyopp/annotation.py
kikyopp/run.py
kikyopp/worker.py
kikyopp.egg-info/PKG-INFO
kikyopp.egg-info/SOURCES.txt
kikyopp.egg-info/dependency_links.txt
kikyopp.egg-info/not-zip-safe
kikyopp.egg-info/requires.txt
kikyopp.egg-info/top_level.txt
kikyopp/consumer/__init__.py
kikyopp/consumer/base.py
kikyopp/consumer/kikyo.py
kikyopp/data_models/__init__.py
kikyopp/data_models/preprocess.py
kikyopp/data_models/search_info.py
kikyopp/utils/__init__.py
kikyopp/utils/logging.py
requirements/test.txt
tests/__init__.py