Metadata-Version: 1.2
Name: kikyopp
Version: 0.21
Summary: kikyo pre-process framework
Home-page: UNKNOWN
Author: jadbin
Author-email: jadbin.com@hotmail.com
License: UNKNOWN
Platform: UNKNOWN
Classifier: License :: OSI Approved :: MIT License
Classifier: Intended Audience :: Developers
Classifier: Programming Language :: Python
Classifier: Programming Language :: Python :: 3
Classifier: Topic :: Software Development :: Libraries :: Python Modules
Requires-Python: >=3.6
